README.md
setup.cfg
setup.py
boltiot/__init__.py
boltiot/alert.py
boltiot/bolt.py
boltiot/requesting.py
boltiot/test.py
boltiot/urls.py
boltiot.egg-info/PKG-INFO
boltiot.egg-info/SOURCES.txt
boltiot.egg-info/dependency_links.txt
boltiot.egg-info/requires.txt
boltiot.egg-info/top_level.txt