Metadata-Version: 1.0
Name: boltiot
Version: 1.7
Summary: A Python module for communicating with the Bolt Cloud API.
Home-page: https://github.com/Inventrom/bolt-api-python
Author: Inventrom Pvt. Ltd.
Author-email: support@boltiot.com
License: UNKNOWN
Keywords: iot-platform,bolt,bolt-python
Platform: UNKNOWN
